odoo/addons/website_sale_coupon_page/README.rst
odoo/addons/website_sale_coupon_page/__init__.py
odoo/addons/website_sale_coupon_page/__manifest__.py
odoo/addons/website_sale_coupon_page/controllers/__init__.py
odoo/addons/website_sale_coupon_page/controllers/main.py
odoo/addons/website_sale_coupon_page/i18n/es.po
odoo/addons/website_sale_coupon_page/i18n/website_sale_coupon_page.pot
odoo/addons/website_sale_coupon_page/models/__init__.py
odoo/addons/website_sale_coupon_page/models/coupon_program.py
odoo/addons/website_sale_coupon_page/readme/CONFIGURE.rst
odoo/addons/website_sale_coupon_page/readme/CONTRIBUTORS.rst
odoo/addons/website_sale_coupon_page/readme/DESCRIPTION.rst
odoo/addons/website_sale_coupon_page/readme/USAGE.rst
odoo/addons/website_sale_coupon_page/static/description/icon.png
odoo/addons/website_sale_coupon_page/static/description/index.html
odoo/addons/website_sale_coupon_page/static/src/js/website_sale_coupon_page_admin.js
odoo/addons/website_sale_coupon_page/static/src/js/website_sale_coupon_page_portal.js
odoo/addons/website_sale_coupon_page/static/src/scss/styles.scss
odoo/addons/website_sale_coupon_page/templates/promotion_templates.xml
odoo/addons/website_sale_coupon_page/tests/__init__.py
odoo/addons/website_sale_coupon_page/tests/test_website_sale_coupon_page.py
odoo/addons/website_sale_coupon_page/views/sale_coupon_program_views.xml
odoo_addon_website_sale_coupon_page-15.0.1.0.0.6.dist-info/METADATA
odoo_addon_website_sale_coupon_page-15.0.1.0.0.6.dist-info/WHEEL
odoo_addon_website_sale_coupon_page-15.0.1.0.0.6.dist-info/top_level.txt
odoo_addon_website_sale_coupon_page-15.0.1.0.0.6.dist-info/RECORD
